lab_practice19-20/MUX_8x1.v
module MUX_8x1(Q,E,O);
input [2:0] Q;
input [7:0] E;
output O;
	assign O = Q[2] ? 
					(Q[1] ? 
						( (Q[0] ? (E[7]) : (E[6]) ) ) 
					:   ( (Q[0] ? (E[5]) : (E[4]) )) ) 
				  : (Q[1] ? 
						( (Q[0] ? (E[3]) : (E[2]) )) 
					:   ( (Q[0] ? (E[1]) : (E[0]) )));
endmodule

lab_practice19-20/MUX_2x1.v
module MUX_2x1(a,b,sel,outp);
input a,b,sel;
output outp;
assign outp=sel?a:b;
endmodule

lab_practice19-20/MUX_ARRAY.v
`include "MUX_2x1.v"
module MUX_ARRAY(B,G,E);
input [7:0] B;
input [7:0] G;
output [7:0] E;
genvar i;
generate
     for(i=0;i<8;i=i+1) begin: for_loop
        MUX_2x1 m1(B[i],1'b0,G[i],E[i]);
     end
endgenerate
endmodule

lab_practice19-20/DECODER.v
module DECODER(A2,A1,A0,B,EN);
input A2,A1,A0;
output reg [7:0] B;
input EN;
always @(A2 or A1 or A0) begin
    if (~EN) B<=8'h00;
    else begin 
    case ({A2,A1,A0})
    3'b000: B<=8'h01;
    3'b001: B<=8'h02;
    3'b010: B<=8'h04;
    3'b011: B<=8'h08;
    3'b100: B<=8'h10;
    3'b101: B<=8'h20;
    3'b110: B<=8'h40;
    3'b111: B<=8'h80;
    endcase
    end
end
endmodule

lab_practice19-20/COUNTER_3BIT.v
module COUNTER_3BIT(clk,clr,Q);
input clk,clr;
output reg [2:0] Q;
initial Q=3'b000;
always @(posedge clk) begin
    // if(clr) Q=3'b000;
    Q<=Q+1;
end
always @(clr) 
    if(clr)Q<=3'b000;
endmodule

lab_practice19-20/MEMORY.v
module MEMORY(add,value);
input [2:0] add;
output reg [7:0] value;
reg [7:0][7:0] tab;
initial begin
    tab[0]<=8'h01;
    tab[1]<=8'h03;
    tab[2]<=8'h07;
    tab[3]<=8'h0f;
    tab[4]<=8'h1f;
    tab[5]<=8'h3f;
    tab[6]<=8'h7f;
    tab[7]<=8'hff;
end
always @(add) begin
    value <= tab[add];
end
endmodule;

lab_practice19-20/TOP_MODULE.v
`timescale 1ms/1ns  
`include "MUX_ARRAY.v"
`include "DECODER.v"
`include "MUX_8x1.v"
`include "MEMORY.v"
`include "COUNTER_3BIT.v"
// `include "MUX_2x1.v"
module TOP_MODULE(clk,clr,en,s2,s1,s0,outp,Q);
input clk,clr,en,s2,s1,s0;
output outp;
output [2:0] Q;
wire [7:0] B,G,E;
MEMORY m({s2,s1,s0},G);
COUNTER_3BIT c(clk,clr,Q);
DECODER d(Q[2],Q[1],Q[0],B,en);
MUX_ARRAY ma(B,G,E);
MUX_8x1 m1(Q,E,outp);
endmodule

module tb;
reg clk,clr,en;
reg [2:0] s;
wire outp;
wire [2:0] Q;
initial clk=0;
always #0.5 clk=~clk;
always #8 s=s+1;
TOP_MODULE tm(clk,clr,en,s[2],s[1],s[0],outp,Q);
initial $monitor($time," s=%b Q=%b outp=%b",s,Q,outp);
initial begin
    #0 clr=1'b1;
    #1 clr=1'b0;s=3'b000;
    
    #500 $finish;
end
initial
 begin
    $dumpfile("TOP_MODULE.vcd");
    $dumpvars;
 end
endmodule

lab_practice19-20/TOP_MODULE.vcd
$date
	Sun Nov 28 08:47:04 2021
$end
$version
	Icarus Verilog
$end
$timescale
	1ns
$end
$scope module tb $end
$var wire 1 ! outp $end
$var wire 3 " Q [2:0] $end
$var reg 1 # clk $end
$var reg 1 $ clr $end
$var reg 1 % en $end
$var reg 3 & s [2:0] $end
$scope module tm $end
$var wire 1 # clk $end
$var wire 1 $ clr $end
$var wire 1 % en $end
$var wire 1 ' s0 $end
$var wire 1 ( s1 $end
$var wire 1 ) s2 $end
$var wire 1 ! outp $end
$var wire 3 * Q [2:0] $end
$var wire 8 + G [7:0] $end
$var wire 8 , E [7:0] $end
$var wire 8 - B [7:0] $end
$scope module c $end
$var wire 1 # clk $end
$var wire 1 $ clr $end
$var reg 3 . Q [2:0] $end
$upscope $end
$scope module d $end
$var wire 1 / A0 $end
$var wire 1 0 A1 $end
$var wire 1 1 A2 $end
$var wire 1 % EN $end
$var reg 8 2 B [7:0] $end
$upscope $end
$scope module m $end
$var wire 3 3 add [2:0] $end
$var reg 64 4 tab [63:0] $end
$var reg 8 5 value [7:0] $end
$upscope $end
$scope module m1 $end
$var wire 3 6 Q [2:0] $end
$var wire 1 ! O $end
$var wire 8 7 E [7:0] $end
$upscope $end
$scope module ma $end
$var wire 8 8 B [7:0] $end
$var wire 8 9 G [7:0] $end
$var wire 8 : E [7:0] $end
$scope begin for_loop[0] $end
$scope module m1 $end
$var wire 1 ; a $end
$var wire 1 < b $end
$var wire 1 = sel $end
$var wire 1 > outp $end
$upscope $end
$upscope $end
$scope begin for_loop[1] $end
$scope module m1 $end
$var wire 1 ? a $end
$var wire 1 @ b $end
$var wire 1 A sel $end
$var wire 1 B outp $end
$upscope $end
$upscope $end
$scope begin for_loop[2] $end
$scope module m1 $end
$var wire 1 C a $end
$var wire 1 D b $end
$var wire 1 E sel $end
$var wire 1 F outp $end
$upscope $end
$upscope $end
$scope begin for_loop[3] $end
$scope module m1 $end
$var wire 1 G a $end
$var wire 1 H b $end
$var wire 1 I sel $end
$var wire 1 J outp $end
$upscope $end
$upscope $end
$scope begin for_loop[4] $end
$scope module m1 $end
$var wire 1 K a $end
$var wire 1 L b $end
$var wire 1 M sel $end
$var wire 1 N outp $end
$upscope $end
$upscope $end
$scope begin for_loop[5] $end
$scope module m1 $end
$var wire 1 O a $end
$var wire 1 P b $end
$var wire 1 Q sel $end
$var wire 1 R outp $end
$upscope $end
$upscope $end
$scope begin for_loop[6] $end
$scope module m1 $end
$var wire 1 S a $end
$var wire 1 T b $end
$var wire 1 U sel $end
$var wire 1 V outp $end
$upscope $end
$upscope $end
$scope begin for_loop[7] $end
$scope module m1 $end
$var wire 1 W a $end
$var wire 1 X b $end
$var wire 1 Y sel $end
$var wire 1 Z outp $end
$upscope $end
$upscope $end
$upscope $end
$upscope $end
$upscope $end
$enddefinitions $end
#0
$dumpvars
0Z
xY
0X
0W
0V
xU
0T
0S
0R
xQ
0P
0O
0N
xM
0L
0K
0J
xI
0H
0G
0F
xE
0D
0C
0B
xA
0@
0?
x>
x=
0<
1;
b0x :
bx 9
b1 8
b0x 7
b0 6
bx 5
b1111111101111111001111110001111100001111000001110000001100000001 4
bx 3
b1 2
01
00
0/
b0 .
b1 -
b0x ,
bx +
b0 *
x)
x(
x'
bx &
x%
1$
0#
b0 "
x!
$end
#500000
0>
b0x0 ,
b0x0 7
b0x0 :
xB
0;
1?
b10 -
b10 2
b10 8
x!
1/
b1 "
b1 *
b1 .
b1 6
1#
#1000000
0!
b0 ,
b0 7
b0 :
0B
1=
0A
0E
0I
0M
0Q
0U
0Y
b1 +
b1 5
b1 9
0)
0(
b0 3
0'
0#
b0 &
0$
#1500000
0?
1C
b100 -
b100 2
b100 8
0/
10
b10 "
b10 *
b10 .
b10 6
1#
#2000000
0#
#2500000
0C
1G
b1000 -
b1000 2
b1000 8
1/
b11 "
b11 *
b11 .
b11 6
1#
#3000000
0#
#3500000
0G
1K
b10000 -
b10000 2
b10000 8
0/
00
11
b100 "
b100 *
b100 .
b100 6
1#
#4000000
0#
#4500000
0K
1O
b100000 -
b100000 2
b100000 8
1/
b101 "
b101 *
b101 .
b101 6
1#
#5000000
0#
#5500000
0O
1S
b1000000 -
b1000000 2
b1000000 8
0/
10
b110 "
b110 *
b110 .
b110 6
1#
#6000000
0#
#6500000
0S
1W
b10000000 -
b10000000 2
b10000000 8
1/
b111 "
b111 *
b111 .
b111 6
1#
#7000000
0#
#7500000
1!
b1 ,
b1 7
b1 :
1>
1;
0W
b1 -
b1 2
b1 8
0/
00
01
b0 "
b0 *
b0 .
b0 6
1#
#8000000
1A
b11 +
b11 5
b11 9
b1 3
1'
0#
b1 &
#8500000
0>
b10 ,
b10 7
b10 :
1B
0;
1?
b10 -
b10 2
b10 8
1!
1/
b1 "
b1 *
b1 .
b1 6
1#
#9000000
0#
#9500000
b0 ,
b0 7
b0 :
0B
0?
1C
b100 -
b100 2
b100 8
0!
0/
10
b10 "
b10 *
b10 .
b10 6
1#
#10000000
0#
#10500000
0C
1G
b1000 -
b1000 2
b1000 8
1/
b11 "
b11 *
b11 .
b11 6
1#
#11000000
0#
#11500000
0G
1K
b10000 -
b10000 2
b10000 8
0/
00
11
b100 "
b100 *
b100 .
b100 6
1#
#12000000
0#
#12500000
0K
1O
b100000 -
b100000 2
b100000 8
1/
b101 "
b101 *
b101 .
b101 6
1#
#13000000
0#
#13500000
0O
1S
b1000000 -
b1000000 2
b1000000 8
0/
10
b110 "
b110 *
b110 .
b110 6
1#
#14000000
0#
#14500000
0S
1W
b10000000 -
b10000000 2
b10000000 8
1/
b111 "
b111 *
b111 .
b111 6
1#
#15000000
0#
#15500000
1!
b1 ,
b1 7
b1 :
1>
1;
0W
b1 -
b1 2
b1 8
0/
00
01
b0 "
b0 *
b0 .
b0 6
1#
#16000000
1E
b111 +
b111 5
b111 9
1(
b10 3
0'
0#
b10 &
#16500000
0>
b10 ,
b10 7
b10 :
1B
0;
1?
b10 -
b10 2
b10 8
1!
1/
b1 "
b1 *
b1 .
b1 6
1#
#17000000
0#
#17500000
0B
b100 ,
b100 7
b100 :
1F
0?
1C
b100 -
b100 2
b100 8
1!
0/
10
b10 "
b10 *
b10 .
b10 6
1#
#18000000
0#
#18500000
b0 ,
b0 7
b0 :
0F
0C
1G
b1000 -
b1000 2
b1000 8
0!
1/
b11 "
b11 *
b11 .
b11 6
1#
#19000000
0#
#19500000
0G
1K
b10000 -
b10000 2
b10000 8
0/
00
11
b100 "
b100 *
b100 .
b100 6
1#
#20000000
0#
#20500000
0K
1O
b100000 -
b100000 2
b100000 8
1/
b101 "
b101 *
b101 .
b101 6
1#
#21000000
0#
#21500000
0O
1S
b1000000 -
b1000000 2
b1000000 8
0/
10
b110 "
b110 *
b110 .
b110 6
1#
#22000000
0#
#22500000
0S
1W
b10000000 -
b10000000 2
b10000000 8
1/
b111 "
b111 *
b111 .
b111 6
1#
#23000000
0#
#23500000
1!
b1 ,
b1 7
b1 :
1>
1;
0W
b1 -
b1 2
b1 8
0/
00
01
b0 "
b0 *
b0 .
b0 6
1#
#24000000
1I
b1111 +
b1111 5
b1111 9
b11 3
1'
0#
b11 &
#24500000
0>
b10 ,
b10 7
b10 :
1B
0;
1?
b10 -
b10 2
b10 8
1!
1/
b1 "
b1 *
b1 .
b1 6
1#
#25000000
0#
#25500000
0B
b100 ,
b100 7
b100 :
1F
0?
1C
b100 -
b100 2
b100 8
1!
0/
10
b10 "
b10 *
b10 .
b10 6
1#
#26000000
0#
#26500000
0F
b1000 ,
b1000 7
b1000 :
1J
0C
1G
b1000 -
b1000 2
b1000 8
1!
1/
b11 "
b11 *
b11 .
b11 6
1#
#27000000
0#
#27500000
b0 ,
b0 7
b0 :
0J
0G
1K
b10000 -
b10000 2
b10000 8
0!
0/
00
11
b100 "
b100 *
b100 .
b100 6
1#
#28000000
0#
#28500000
0K
1O
b100000 -
b100000 2
b100000 8
1/
b101 "
b101 *
b101 .
b101 6
1#
#29000000
0#
#29500000
0O
1S
b1000000 -
b1000000 2
b1000000 8
0/
10
b110 "
b110 *
b110 .
b110 6
1#
#30000000
0#
#30500000
0S
1W
b10000000 -
b10000000 2
b10000000 8
1/
b111 "
b111 *
b111 .
b111 6
1#
#31000000
0#
#31500000
1!
b1 ,
b1 7
b1 :
1>
1;
0W
b1 -
b1 2
b1 8
0/
00
01
b0 "
b0 *
b0 .
b0 6
1#
#32000000
1M
b11111 +
b11111 5
b11111 9
1)
0(
b100 3
0'
0#
b100 &
#32500000
0>
b10 ,
b10 7
b10 :
1B
0;
1?
b10 -
b10 2
b10 8
1!
1/
b1 "
b1 *
b1 .
b1 6
1#
#33000000
0#
#33500000
0B
b100 ,
b100 7
b100 :
1F
0?
1C
b100 -
b100 2
b100 8
1!
0/
10
b10 "
b10 *
b10 .
b10 6
1#
#34000000
0#
#34500000
0F
b1000 ,
b1000 7
b1000 :
1J
0C
1G
b1000 -
b1000 2
b1000 8
1!
1/
b11 "
b11 *
b11 .
b11 6
1#
#35000000
0#
#35500000
0J
b10000 ,
b10000 7
b10000 :
1N
0G
1K
b10000 -
b10000 2
b10000 8
1!
0/
00
11
b100 "
b100 *
b100 .
b100 6
1#
#36000000
0#
#36500000
b0 ,
b0 7
b0 :
0N
0K
1O
b100000 -
b100000 2
b100000 8
0!
1/
b101 "
b101 *
b101 .
b101 6
1#
#37000000
0#
#37500000
0O
1S
b1000000 -
b1000000 2
b1000000 8
0/
10
b110 "
b110 *
b110 .
b110 6
1#
#38000000
0#
#38500000
0S
1W
b10000000 -
b10000000 2
b10000000 8
1/
b111 "
b111 *
b111 .
b111 6
1#
#39000000
0#
#39500000
1!
b1 ,
b1 7
b1 :
1>
1;
0W
b1 -
b1 2
b1 8
0/
00
01
b0 "
b0 *
b0 .
b0 6
1#
#40000000
1Q
b111111 +
b111111 5
b111111 9
b101 3
1'
0#
b101 &
#40500000
0>
b10 ,
b10 7
b10 :
1B
0;
1?
b10 -
b10 2
b10 8
1!
1/
b1 "
b1 *
b1 .
b1 6
1#
#41000000
0#
#41500000
0B
b100 ,
b100 7
b100 :
1F
0?
1C
b100 -
b100 2
b100 8
1!
0/
10
b10 "
b10 *
b10 .
b10 6
1#
#42000000
0#
#42500000
0F
b1000 ,
b1000 7
b1000 :
1J
0C
1G
b1000 -
b1000 2
b1000 8
1!
1/
b11 "
b11 *
b11 .
b11 6
1#
#43000000
0#
#43500000
0J
b10000 ,
b10000 7
b10000 :
1N
0G
1K
b10000 -
b10000 2
b10000 8
1!
0/
00
11
b100 "
b100 *
b100 .
b100 6
1#
#44000000
0#
#44500000
0N
b100000 ,
b100000 7
b100000 :
1R
0K
1O
b100000 -
b100000 2
b100000 8
1!
1/
b101 "
b101 *
b101 .
b101 6
1#
#45000000
0#
#45500000
b0 ,
b0 7
b0 :
0R
0O
1S
b1000000 -
b1000000 2
b1000000 8
0!
0/
10
b110 "
b110 *
b110 .
b110 6
1#
#46000000
0#
#46500000
0S
1W
b10000000 -
b10000000 2
b10000000 8
1/
b111 "
b111 *
b111 .
b111 6
1#
#47000000
0#
#47500000
1!
b1 ,
b1 7
b1 :
1>
1;
0W
b1 -
b1 2
b1 8
0/
00
01
b0 "
b0 *
b0 .
b0 6
1#
#48000000
1U
b1111111 +
b1111111 5
b1111111 9
1(
b110 3
0'
0#
b110 &
#48500000
0>
b10 ,
b10 7
b10 :
1B
0;
1?
b10 -
b10 2
b10 8
1!
1/
b1 "
b1 *
b1 .
b1 6
1#
#49000000
0#
#49500000
0B
b100 ,
b100 7
b100 :
1F
0?
1C
b100 -
b100 2
b100 8
1!
0/
10
b10 "
b10 *
b10 .
b10 6
1#
#50000000
0#
#50500000
0F
b1000 ,
b1000 7
b1000 :
1J
0C
1G
b1000 -
b1000 2
b1000 8
1!
1/
b11 "
b11 *
b11 .
b11 6
1#
#51000000
0#
#51500000
0J
b10000 ,
b10000 7
b10000 :
1N
0G
1K
b10000 -
b10000 2
b10000 8
1!
0/
00
11
b100 "
b100 *
b100 .
b100 6
1#
#52000000
0#
#52500000
0N
b100000 ,
b100000 7
b100000 :
1R
0K
1O
b100000 -
b100000 2
b100000 8
1!
1/
b101 "
b101 *
b101 .
b101 6
1#
#53000000
0#
#53500000
0R
b1000000 ,
b1000000 7
b1000000 :
1V
0O
1S
b1000000 -
b1000000 2
b1000000 8
1!
0/
10
b110 "
b110 *
b110 .
b110 6
1#
#54000000
0#
#54500000
b0 ,
b0 7
b0 :
0V
0S
1W
b10000000 -
b10000000 2
b10000000 8
0!
1/
b111 "
b111 *
b111 .
b111 6
1#
#55000000
0#
#55500000
1!
b1 ,
b1 7
b1 :
1>
1;
0W
b1 -
b1 2
b1 8
0/
00
01
b0 "
b0 *
b0 .
b0 6
1#
#56000000
1Y
b11111111 +
b11111111 5
b11111111 9
b111 3
1'
0#
b111 &
#56500000
0>
b10 ,
b10 7
b10 :
1B
0;
1?
b10 -
b10 2
b10 8
1!
1/
b1 "
b1 *
b1 .
b1 6
1#
#57000000
0#
#57500000
0B
b100 ,
b100 7
b100 :
1F
0?
1C
b100 -
b100 2
b100 8
1!
0/
10
b10 "
b10 *
b10 .
b10 6
1#
#58000000
0#
#58500000
0F
b1000 ,
b1000 7
b1000 :
1J
0C
1G
b1000 -
b1000 2
b1000 8
1!
1/
b11 "
b11 *
b11 .
b11 6
1#
#59000000
0#
#59500000
0J
b10000 ,
b10000 7
b10000 :
1N
0G
1K
b10000 -
b10000 2
b10000 8
1!
0/
00
11
b100 "
b100 *
b100 .
b100 6
1#
#60000000
0#
#60500000
0N
b100000 ,
b100000 7
b100000 :
1R
0K
1O
b100000 -
b100000 2
b100000 8
1!
1/
b101 "
b101 *
b101 .
b101 6
1#
#61000000
0#
#61500000
0R
b1000000 ,
b1000000 7
b1000000 :
1V
0O
1S
b1000000 -
b1000000 2
b1000000 8
1!
0/
10
b110 "
b110 *
b110 .
b110 6
1#
#62000000
0#
#62500000
0V
b10000000 ,
b10000000 7
b10000000 :
1Z
0S
1W
b10000000 -
b10000000 2
b10000000 8
1!
1/
b111 "
b111 *
b111 .
b111 6
1#
#63000000
0#
#63500000
1>
b1 ,
b1 7
b1 :
0Z
1;
0W
b1 -
b1 2
b1 8
1!
0/
00
01
b0 "
b0 *
b0 .
b0 6
1#
#64000000
0A
0E
0I
0M
0Q
0U
0Y
b1 +
b1 5
b1 9
0)
0(
b0 3
0'
0#
b0 &
#64500000
b0 ,
b0 7
b0 :
0>
0;
1?
b10 -
b10 2
b10 8
0!
1/
b1 "
b1 *
b1 .
b1 6
1#
#65000000
0#
#65500000
0?
1C
b100 -
b100 2
b100 8
0/
10
b10 "
b10 *
b10 .
b10 6
1#
#66000000
0#
#66500000
0C
1G
b1000 -
b1000 2
b1000 8
1/
b11 "
b11 *
b11 .
b11 6
1#
#67000000
0#
#67500000
0G
1K
b10000 -
b10000 2
b10000 8
0/
00
11
b100 "
b100 *
b100 .
b100 6
1#
#68000000
0#
#68500000
0K
1O
b100000 -
b100000 2
b100000 8
1/
b101 "
b101 *
b101 .
b101 6
1#
#69000000
0#
#69500000
0O
1S
b1000000 -
b1000000 2
b1000000 8
0/
10
b110 "
b110 *
b110 .
b110 6
1#
#70000000
0#
#70500000
0S
1W
b10000000 -
b10000000 2
b10000000 8
1/
b111 "
b111 *
b111 .
b111 6
1#
#71000000
0#
#71500000
1!
b1 ,
b1 7
b1 :
1>
1;
0W
b1 -
b1 2
b1 8
0/
00
01
b0 "
b0 *
b0 .
b0 6
1#
#72000000
1A
b11 +
b11 5
b11 9
b1 3
1'
0#
b1 &
#72500000
0>
b10 ,
b10 7
b10 :
1B
0;
1?
b10 -
b10 2
b10 8
1!
1/
b1 "
b1 *
b1 .
b1 6
1#
#73000000
0#
#73500000
b0 ,
b0 7
b0 :
0B
0?
1C
b100 -
b100 2
b100 8
0!
0/
10
b10 "
b10 *
b10 .
b10 6
1#
#74000000
0#
#74500000
0C
1G
b1000 -
b1000 2
b1000 8
1/
b11 "
b11 *
b11 .
b11 6
1#
#75000000
0#
#75500000
0G
1K
b10000 -
b10000 2
b10000 8
0/
00
11
b100 "
b100 *
b100 .
b100 6
1#
#76000000
0#
#76500000
0K
1O
b100000 -
b100000 2
b100000 8
1/
b101 "
b101 *
b101 .
b101 6
1#
#77000000
0#
#77500000
0O
1S
b1000000 -
b1000000 2
b1000000 8
0/
10
b110 "
b110 *
b110 .
b110 6
1#
#78000000
0#
#78500000
0S
1W
b10000000 -
b10000000 2
b10000000 8
1/
b111 "
b111 *
b111 .
b111 6
1#
#79000000
0#
#79500000
1!
b1 ,
b1 7
b1 :
1>
1;
0W
b1 -
b1 2
b1 8
0/
00
01
b0 "
b0 *
b0 .
b0 6
1#
#80000000
1E
b111 +
b111 5
b111 9
1(
b10 3
0'
0#
b10 &
#80500000
0>
b10 ,
b10 7
b10 :
1B
0;
1?
b10 -
b10 2
b10 8
1!
1/
b1 "
b1 *
b1 .
b1 6
1#
#81000000
0#
#81500000
0B
b100 ,
b100 7
b100 :
1F
0?
1C
b100 -
b100 2
b100 8
1!
0/
10
b10 "
b10 *
b10 .
b10 6
1#
#82000000
0#
#82500000
b0 ,
b0 7
b0 :
0F
0C
1G
b1000 -
b1000 2
b1000 8
0!
1/
b11 "
b11 *
b11 .
b11 6
1#
#83000000
0#
#83500000
0G
1K
b10000 -
b10000 2
b10000 8
0/
00
11
b100 "
b100 *
b100 .
b100 6
1#
#84000000
0#
#84500000
0K
1O
b100000 -
b100000 2
b100000 8
1/
b101 "
b101 *
b101 .
b101 6
1#
#85000000
0#
#85500000
0O
1S
b1000000 -
b1000000 2
b1000000 8
0/
10
b110 "
b110 *
b110 .
b110 6
1#
#86000000
0#
#86500000
0S
1W
b10000000 -
b10000000 2
b10000000 8
1/
b111 "
b111 *
b111 .
b111 6
1#
#87000000
0#
#87500000
1!
b1 ,
b1 7
b1 :
1>
1;
0W
b1 -
b1 2
b1 8
0/
00
01
b0 "
b0 *
b0 .
b0 6
1#
#88000000
1I
b1111 +
b1111 5
b1111 9
b11 3
1'
0#
b11 &
#88500000
0>
b10 ,
b10 7
b10 :
1B
0;
1?
b10 -
b10 2
b10 8
1!
1/
b1 "
b1 *
b1 .
b1 6
1#
#89000000
0#
#89500000
0B
b100 ,
b100 7
b100 :
1F
0?
1C
b100 -
b100 2
b100 8
1!
0/
10
b10 "
b10 *
b10 .
b10 6
1#
#90000000
0#
#90500000
0F
b1000 ,
b1000 7
b1000 :
1J
0C
1G
b1000 -
b1000 2
b1000 8
1!
1/
b11 "
b11 *
b11 .
b11 6
1#
#91000000
0#
#91500000
b0 ,
b0 7
b0 :
0J
0G
1K
b10000 -
b10000 2
b10000 8
0!
0/
00
11
b100 "
b100 *
b100 .
b100 6
1#
#92000000
0#
#92500000
0K
1O
b100000 -
b100000 2
b100000 8
1/
b101 "
b101 *
b101 .
b101 6
1#
#93000000
0#
#93500000
0O
1S
b1000000 -
b1000000 2
b1000000 8
0/
10
b110 "
b110 *
b110 .
b110 6
1#
#94000000
0#
#94500000
0S
1W
b10000000 -
b10000000 2
b10000000 8
1/
b111 "
b111 *
b111 .
b111 6
1#
#95000000
0#
#95500000
1!
b1 ,
b1 7
b1 :
1>
1;
0W
b1 -
b1 2
b1 8
0/
00
01
b0 "
b0 *
b0 .
b0 6
1#
#96000000
1M
b11111 +
b11111 5
b11111 9
1)
0(
b100 3
0'
0#
b100 &
#96500000
0>
b10 ,
b10 7
b10 :
1B
0;
1?
b10 -
b10 2
b10 8
1!
1/
b1 "
b1 *
b1 .
b1 6
1#
#97000000
0#
#97500000
0B
b100 ,
b100 7
b100 :
1F
0?
1C
b100 -
b100 2
b100 8
1!
0/
10
b10 "
b10 *
b10 .
b10 6
1#
#98000000
0#
#98500000
0F
b1000 ,
b1000 7
b1000 :
1J
0C
1G
b1000 -
b1000 2
b1000 8
1!
1/
b11 "
b11 *
b11 .
b11 6
1#
#99000000
0#
#99500000
0J
b10000 ,
b10000 7
b10000 :
1N
0G
1K
b10000 -
b10000 2
b10000 8
1!
0/
00
11
b100 "
b100 *
b100 .
b100 6
1#
#100000000
0#
#100500000
b0 ,
b0 7
b0 :
0N
0K
1O
b100000 -
b100000 2
b100000 8
0!
1/
b101 "
b101 *
b101 .
b101 6
1#
#101000000
0#
#101500000
0O
1S
b1000000 -
b1000000 2
b1000000 8
0/
10
b110 "
b110 *
b110 .
b110 6
1#
#102000000
0#
#102500000
0S
1W
b10000000 -
b10000000 2
b10000000 8
1/
b111 "
b111 *
b111 .
b111 6
1#
#103000000
0#
#103500000
1!
b1 ,
b1 7
b1 :
1>
1;
0W
b1 -
b1 2
b1 8
0/
00
01
b0 "
b0 *
b0 .
b0 6
1#
#104000000
1Q
b111111 +
b111111 5
b111111 9
b101 3
1'
0#
b101 &
#104500000
0>
b10 ,
b10 7
b10 :
1B
0;
1?
b10 -
b10 2
b10 8
1!
1/
b1 "
b1 *
b1 .
b1 6
1#
#105000000
0#
#105500000
0B
b100 ,
b100 7
b100 :
1F
0?
1C
b100 -
b100 2
b100 8
1!
0/
10
b10 "
b10 *
b10 .
b10 6
1#
#106000000
0#
#106500000
0F
b1000 ,
b1000 7
b1000 :
1J
0C
1G
b1000 -
b1000 2
b1000 8
1!
1/
b11 "
b11 *
b11 .
b11 6
1#
#107000000
0#
#107500000
0J
b10000 ,
b10000 7
b10000 :
1N
0G
1K
b10000 -
b10000 2
b10000 8
1!
0/
00
11
b100 "
b100 *
b100 .
b100 6
1#
#108000000
0#
#108500000
0N
b100000 ,
b100000 7
b100000 :
1R
0K
1O
b100000 -
b100000 2
b100000 8
1!
1/
b101 "
b101 *
b101 .
b101 6
1#
#109000000
0#
#109500000
b0 ,
b0 7
b0 :
0R
0O
1S
b1000000 -
b1000000 2
b1000000 8
0!
0/
10
b110 "
b110 *
b110 .
b110 6
1#
#110000000
0#
#110500000
0S
1W
b10000000 -
b10000000 2
b10000000 8
1/
b111 "
b111 *
b111 .
b111 6
1#
#111000000
0#
#111500000
1!
b1 ,
b1 7
b1 :
1>
1;
0W
b1 -
b1 2
b1 8
0/
00
01
b0 "
b0 *
b0 .
b0 6
1#
#112000000
1U
b1111111 +
b1111111 5
b1111111 9
1(
b110 3
0'
0#
b110 &
#112500000
0>
b10 ,
b10 7
b10 :
1B
0;
1?
b10 -
b10 2
b10 8
1!
1/
b1 "
b1 *
b1 .
b1 6
1#
#113000000
0#
#113500000
0B
b100 ,
b100 7
b100 :
1F
0?
1C
b100 -
b100 2
b100 8
1!
0/
10
b10 "
b10 *
b10 .
b10 6
1#
#114000000
0#
#114500000
0F
b1000 ,
b1000 7
b1000 :
1J
0C
1G
b1000 -
b1000 2
b1000 8
1!
1/
b11 "
b11 *
b11 .
b11 6
1#
#115000000
0#
#115500000
0J
b10000 ,
b10000 7
b10000 :
1N
0G
1K
b10000 -
b10000 2
b10000 8
1!
0/
00
11
b100 "
b100 *
b100 .
b100 6
1#
#116000000
0#
#116500000
0N
b100000 ,
b100000 7
b100000 :
1R
0K
1O
b100000 -
b100000 2
b100000 8
1!
1/
b101 "
b101 *
b101 .
b101 6
1#
#117000000
0#
#117500000
0R
b1000000 ,
b1000000 7
b1000000 :
1V
0O
1S
b1000000 -
b1000000 2
b1000000 8
1!
0/
10
b110 "
b110 *
b110 .
b110 6
1#
#118000000
0#
#118500000
b0 ,
b0 7
b0 :
0V
0S
1W
b10000000 -
b10000000 2
b10000000 8
0!
1/
b111 "
b111 *
b111 .
b111 6
1#
#119000000
0#
#119500000
1!
b1 ,
b1 7
b1 :
1>
1;
0W
b1 -
b1 2
b1 8
0/
00
01
b0 "
b0 *
b0 .
b0 6
1#
#120000000
1Y
b11111111 +
b11111111 5
b11111111 9
b111 3
1'
0#
b111 &
#120500000
0>
b10 ,
b10 7
b10 :
1B
0;
1?
b10 -
b10 2
b10 8
1!
1/
b1 "
b1 *
b1 .
b1 6
1#
#121000000
0#
#121500000
0B
b100 ,
b100 7
b100 :
1F
0?
1C
b100 -
b100 2
b100 8
1!
0/
10
b10 "
b10 *
b10 .
b10 6
1#
#122000000
0#
#122500000
0F
b1000 ,
b1000 7
b1000 :
1J
0C
1G
b1000 -
b1000 2
b1000 8
1!
1/
b11 "
b11 *
b11 .
b11 6
1#
#123000000
0#
#123500000
0J
b10000 ,
b10000 7
b10000 :
1N
0G
1K
b10000 -
b10000 2
b10000 8
1!
0/
00
11
b100 "
b100 *
b100 .
b100 6
1#
#124000000
0#
#124500000
0N
b100000 ,
b100000 7
b100000 :
1R
0K
1O
b100000 -
b100000 2
b100000 8
1!
1/
b101 "
b101 *
b101 .
b101 6
1#
#125000000
0#
#125500000
0R
b1000000 ,
b1000000 7
b1000000 :
1V
0O
1S
b1000000 -
b1000000 2
b1000000 8
1!
0/
10
b110 "
b110 *
b110 .
b110 6
1#
#126000000
0#
#126500000
0V
b10000000 ,
b10000000 7
b10000000 :
1Z
0S
1W
b10000000 -
b10000000 2
b10000000 8
1!
1/
b111 "
b111 *
b111 .
b111 6
1#
#127000000
0#
#127500000
1>
b1 ,
b1 7
b1 :
0Z
1;
0W
b1 -
b1 2
b1 8
1!
0/
00
01
b0 "
b0 *
b0 .
b0 6
1#
#128000000
0A
0E
0I
0M
0Q
0U
0Y
b1 +
b1 5
b1 9
0)
0(
b0 3
0'
0#
b0 &
#128500000
b0 ,
b0 7
b0 :
0>
0;
1?
b10 -
b10 2
b10 8
0!
1/
b1 "
b1 *
b1 .
b1 6
1#
#129000000
0#
#129500000
0?
1C
b100 -
b100 2
b100 8
0/
10
b10 "
b10 *
b10 .
b10 6
1#
#130000000
0#
#130500000
0C
1G
b1000 -
b1000 2
b1000 8
1/
b11 "
b11 *
b11 .
b11 6
1#
#131000000
0#
#131500000
0G
1K
b10000 -
b10000 2
b10000 8
0/
00
11
b100 "
b100 *
b100 .
b100 6
1#
#132000000
0#
#132500000
0K
1O
b100000 -
b100000 2
b100000 8
1/
b101 "
b101 *
b101 .
b101 6
1#
#133000000
0#
#133500000
0O
1S
b1000000 -
b1000000 2
b1000000 8
0/
10
b110 "
b110 *
b110 .
b110 6
1#
#134000000
0#
#134500000
0S
1W
b10000000 -
b10000000 2
b10000000 8
1/
b111 "
b111 *
b111 .
b111 6
1#
#135000000
0#
#135500000
1!
b1 ,
b1 7
b1 :
1>
1;
0W
b1 -
b1 2
b1 8
0/
00
01
b0 "
b0 *
b0 .
b0 6
1#
#136000000
1A
b11 +
b11 5
b11 9
b1 3
1'
0#
b1 &
